skit_auth/__init__.py
skit_auth/auth.py
skit_auth/cli.py
skit_auth/constants.py
skit_auth/utils.py
skit_auth-0.1.5.dist-info/entry_points.txt
skit_auth-0.1.5.dist-info/LICENSE
skit_auth-0.1.5.dist-info/WHEEL
skit_auth-0.1.5.dist-info/METADATA
skit_auth-0.1.5.dist-info/RECORD
