Metadata-Version: 2.1
Name: skit-auth
Version: 0.1.5
Summary: Authorization for skit.ai's platform.
Home-page: https://github.com/skit-ai/skit-auth
License: GPL-3.0-only
Author: ltbringer
Author-email: amresh.venugopal@gmail.com
Requires-Python: >=3.8,<3.11
Classifier: License :: OSI Approved :: GNU General Public License v3 (GPLv3)
Classifier: Programming Language :: Python :: 3
Classifier: Programming Language :: Python :: 3.10
Classifier: Programming Language :: Python :: 3.8
Classifier: Programming Language :: Python :: 3.9
Requires-Dist: loguru (>=0.5.3,<0.6.0)
Requires-Dist: requests (>=2.27.1,<3.0.0)
Requires-Dist: requests-mock (>=1.9.3,<2.0.0)
Requires-Dist: toml (>=0.10.2,<0.11.0)
Project-URL: Repository, https://github.com/skit-ai/skit-auth
